{
    "GBAPath":"/Users/abelmathew/Desktop/Grad School Stuff/Semester 2//VDA2/Project/Files/GBA",
    "PBAPath":"/Users/abelmathew/Desktop/Grad School Stuff/Semester 2/VDA2/Project/Files/PBA",
    "OutfilePath":"/Users/abelmathew/Desktop/Grad School Stuff/Semester 2/VDA2/Project/OutFiles/",
    "pbapredictpath":"/Users/abelmathew/Desktop/Grad School Stuff/Semester 2/VDA2/Project/Prediction Files/PBA/pba_pipo.timing_setup.rpt",
    "gbapredictpath":"/Users/abelmathew/Desktop/Grad School Stuff/Semester 2/VDA2/Project/Prediction Files/GBA/gba_pipo.timing_setup.rpt"
}